sordid/__init__.py
sordid/scan.py
sordid-0.1.0.dist-info/METADATA
sordid-0.1.0.dist-info/WHEEL
sordid-0.1.0.dist-info/RECORD
