Metadata-Version: 2.1
Name: sordid
Version: 0.1.0
Summary: This is just a small description
Author: François Proulx
Author-email: francois@boostsecurity.io
Requires-Python: >=3.10,<4.0
Classifier: Programming Language :: Python :: 3
Classifier: Programming Language :: Python :: 3.10
Classifier: Programming Language :: Python :: 3.11
Requires-Dist: build (>=0.10.0,<0.11.0)
Requires-Dist: twine (>=4.0.2,<5.0.0)
